dirtyfields/__init__.py
dirtyfields/compare.py
dirtyfields/dirtyfields.py
django_dirtyfields-1.9.5.dist-info/LICENSE
django_dirtyfields-1.9.5.dist-info/METADATA
django_dirtyfields-1.9.5.dist-info/WHEEL
django_dirtyfields-1.9.5.dist-info/top_level.txt
django_dirtyfields-1.9.5.dist-info/RECORD
