Metadata-Version: 2.1
Name: django-dirtyfields
Version: 1.9.5
Summary: Tracking dirty fields on a Django model instance.
Author: Romain Garrigues
Maintainer: Lincoln Puzey
License: Copyright (c) Praekelt Foundation and individual contributors.
Project-URL: Homepage, https://github.com/romgar/django-dirtyfields
Project-URL: Repository, https://github.com/romgar/django-dirtyfields.git
Project-URL: Changelog, https://github.com/romgar/django-dirtyfields/blob/develop/ChangeLog.rst
Project-URL: Documentation, https://django-dirtyfields.readthedocs.io
Keywords: django,dirtyfields,track,model,changes
Classifier: Development Status :: 5 - Production/Stable
Classifier: Intended Audience :: Developers
Classifier: Topic :: Software Development :: Libraries :: Python Modules
Classifier: License :: OSI Approved :: BSD License
Classifier: Natural Language :: English
Classifier: Operating System :: OS Independent
Classifier: Programming Language :: Python
Classifier: Programming Language :: Python :: 3
Classifier: Programming Language :: Python :: 3 :: Only
Classifier: Programming Language :: Python :: 3.9
Classifier: Programming Language :: Python :: 3.10
Classifier: Programming Language :: Python :: 3.11
Classifier: Programming Language :: Python :: 3.12
Classifier: Programming Language :: Python :: 3.13
Classifier: Framework :: Django
Classifier: Framework :: Django :: 2.2
Classifier: Framework :: Django :: 3.0
Classifier: Framework :: Django :: 3.1
Classifier: Framework :: Django :: 3.2
Classifier: Framework :: Django :: 4.0
Classifier: Framework :: Django :: 4.1
Classifier: Framework :: Django :: 4.2
Classifier: Framework :: Django :: 5.0
Classifier: Framework :: Django :: 5.1
Requires-Python: >=3.9
License-File: LICENSE
Requires-Dist: Django>=2.2
